gitprofile/__init__.py
gitprofile/__main__.py
gitprofile/_version.py
gitprofile/cli.py
git_profile_cli-1.0.2.dist-info/LICENSE
git_profile_cli-1.0.2.dist-info/METADATA
git_profile_cli-1.0.2.dist-info/WHEEL
git_profile_cli-1.0.2.dist-info/entry_points.txt
git_profile_cli-1.0.2.dist-info/top_level.txt
git_profile_cli-1.0.2.dist-info/RECORD
