Metadata-Version: 2.1
Name: git-profile-cli
Version: 1.0.2
Summary: Git-Profile-cli is a CLI tool that simplifies switching between multiple Git profiles—user names, emails, and SSH keys—ideal for developers working on various projects or with multiple organizations.
Author-email: Walid Karray <walid.karray@gmail.com>
License: MIT License
Project-URL: Homepage, https://github.com/tux86/git-profile-cli
Project-URL: Bug Tracker, https://github.com/tux86/git-profile-cli/issues
Keywords: git,profile,management,cli
Classifier: Programming Language :: Python :: 3
Classifier: License :: OSI Approved :: MIT License
Classifier: Operating System :: OS Independent
Requires-Python: >=3.6
License-File: LICENSE
Requires-Dist: PyYAML>=6.0.1
Requires-Dist: inquirer>=2.10.0
